<?xml version="1.0" encoding="UTF-8"?>
<sdf3 type="sdf" version="1.0"
    xmlns:xsi="http://www.w3.org/2001/XMLSchema-instance"
    xsi:noNamespaceSchemaLocation="http://www.es.ele.tue.nl/sdf3/xsd/sdf3-csdf.xsd">
<applicationGraph name='fir'>
    <sdf name='fir' type='fir'>
        <actor name='0x2b962a0' type='1'>
            <port type='out' name='in_channel_25_real' rate='1'/>
            <port type='out' name='in_R0x2b962a0' rate='1'/>
            <port type='in' name='out_R0x2b962a0' rate='1'/>
        </actor>
        <actor name='0x2ba41a0' type='2'>
            <port type='out' name='in_channel_19_int' rate='1'/>
            <port type='out' name='in_channel_27_int' rate='1'/>
            <port type='out' name='in_channel_33_int' rate='1'/>
            <port type='out' name='in_R0x2ba41a0' rate='1'/>
            <port type='in' name='out_R0x2ba41a0' rate='1'/>
        </actor>
        <actor name='0x2bab8a0' type='REC W0'>
            <port type='in' name='out_channel_37_real' rate='1'/>
            <port type='out' name='in_channel_38_real' rate='1'/>
            <port type='out' name='in_R0x2bab8a0' rate='1'/>
            <port type='in' name='out_R0x2bab8a0' rate='1'/>
        </actor>
        <actor name='0x2babca0' type='Proj0'>
            <port type='in' name='out_channel_38_real' rate='1'/>
            <port type='out' name='in_channel_41_real' rate='1'/>
            <port type='out' name='in_channel_15_real' rate='1'/>
            <port type='out' name='in_channel_20_real' rate='1'/>
            <port type='out' name='in_R0x2babca0' rate='1'/>
            <port type='in' name='out_R0x2babca0' rate='1'/>
        </actor>
        <actor name='0x2bad3d0' type='2'>
            <port type='out' name='in_channel_7_real' rate='1'/>
            <port type='out' name='in_R0x2bad3d0' rate='1'/>
            <port type='in' name='out_R0x2bad3d0' rate='1'/>
        </actor>
        <actor name='0x2baf8e0' type='float'>
            <port type='in' name='out_channel_2_int' rate='1'/>
            <port type='out' name='in_channel_3_real' rate='1'/>
            <port type='out' name='in_channel_9_real' rate='1'/>
            <port type='out' name='in_R0x2baf8e0' rate='1'/>
            <port type='in' name='out_R0x2baf8e0' rate='1'/>
        </actor>
        <actor name='0x2baf9f0' type='div'>
            <port type='in' name='out_channel_1_real' rate='1'/>
            <port type='in' name='out_channel_3_real' rate='1'/>
            <port type='out' name='in_channel_4_real' rate='1'/>
            <port type='out' name='in_R0x2baf9f0' rate='1'/>
            <port type='in' name='out_R0x2baf9f0' rate='1'/>
        </actor>
        <actor name='0x2bb0720' type='div'>
            <port type='in' name='out_channel_8_real' rate='1'/>
            <port type='in' name='out_channel_9_real' rate='1'/>
            <port type='out' name='in_channel_10_real' rate='1'/>
            <port type='out' name='in_R0x2bb0720' rate='1'/>
            <port type='in' name='out_R0x2bb0720' rate='1'/>
        </actor>
        <actor name='0x2bb0850' type='cos'>
            <port type='in' name='out_channel_10_real' rate='1'/>
            <port type='out' name='in_channel_11_real' rate='1'/>
            <port type='out' name='in_R0x2bb0850' rate='1'/>
            <port type='in' name='out_R0x2bb0850' rate='1'/>
        </actor>
        <actor name='0x2bb1870' type='-1'>
            <port type='out' name='in_channel_0_int' rate='1'/>
            <port type='out' name='in_R0x2bb1870' rate='1'/>
            <port type='in' name='out_R0x2bb1870' rate='1'/>
        </actor>
        <actor name='0x2bb1920' type='prod'>
            <port type='in' name='out_channel_0_int' rate='1'/>
            <port type='in' name='out_channel_4_real' rate='1'/>
            <port type='out' name='in_channel_5_real' rate='1'/>
            <port type='out' name='in_R0x2bb1920' rate='1'/>
            <port type='in' name='out_R0x2bb1920' rate='1'/>
        </actor>
        <actor name='0x2bb1a10' type='exp'>
            <port type='in' name='out_channel_5_real' rate='1'/>
            <port type='out' name='in_channel_6_real' rate='1'/>
            <port type='out' name='in_channel_17_real' rate='1'/>
            <port type='out' name='in_channel_26_real' rate='1'/>
            <port type='out' name='in_R0x2bb1a10' rate='1'/>
            <port type='in' name='out_R0x2bb1a10' rate='1'/>
        </actor>
        <actor name='0x2bb2a10' type='pow'>
            <port type='in' name='out_channel_26_real' rate='1'/>
            <port type='in' name='out_channel_27_int' rate='1'/>
            <port type='out' name='in_channel_28_real' rate='1'/>
            <port type='out' name='in_R0x2bb2a10' rate='1'/>
            <port type='in' name='out_R0x2bb2a10' rate='1'/>
        </actor>
        <actor name='0x2bb35c0' type='prod'>
            <port type='in' name='out_channel_17_real' rate='1'/>
            <port type='in' name='out_channel_20_real' rate='1'/>
            <port type='out' name='in_channel_21_real' rate='1'/>
            <port type='out' name='in_R0x2bb35c0' rate='1'/>
            <port type='in' name='out_R0x2bb35c0' rate='1'/>
        </actor>
        <actor name='0x2bb3760' type='prod'>
            <port type='in' name='out_channel_7_real' rate='1'/>
            <port type='in' name='out_channel_11_real' rate='1'/>
            <port type='out' name='in_channel_12_real' rate='1'/>
            <port type='out' name='in_R0x2bb3760' rate='1'/>
            <port type='in' name='out_R0x2bb3760' rate='1'/>
        </actor>
        <actor name='0x2bb3850' type='prod'>
            <port type='in' name='out_channel_12_real' rate='1'/>
            <port type='in' name='out_channel_15_real' rate='1'/>
            <port type='out' name='in_channel_16_real' rate='1'/>
            <port type='out' name='in_R0x2bb3850' rate='1'/>
            <port type='in' name='out_R0x2bb3850' rate='1'/>
        </actor>
        <actor name='0x2bb3940' type='diff'>
            <port type='in' name='out_channel_16_real' rate='1'/>
            <port type='in' name='out_channel_21_real' rate='1'/>
            <port type='out' name='in_channel_22_real' rate='1'/>
            <port type='out' name='in_R0x2bb3940' rate='1'/>
            <port type='in' name='out_R0x2bb3940' rate='1'/>
        </actor>
        <actor name='0x2bb3a30' type='prod'>
            <port type='in' name='out_channel_6_real' rate='1'/>
            <port type='in' name='out_channel_22_real' rate='1'/>
            <port type='out' name='in_channel_23_real' rate='1'/>
            <port type='out' name='in_R0x2bb3a30' rate='1'/>
            <port type='in' name='out_R0x2bb3a30' rate='1'/>
        </actor>
        <actor name='0x2bb3fe0' type='diff'>
            <port type='in' name='out_channel_31_real_vect' rate='1'/>
            <port type='in' name='out_channel_34_real_vect' rate='1'/>
            <port type='out' name='in_channel_35_real_vect' rate='1'/>
            <port type='out' name='in_R0x2bb3fe0' rate='1'/>
            <port type='in' name='out_R0x2bb3fe0' rate='1'/>
        </actor>
        <actor name='0x2bb41a0' type='diff'>
            <port type='in' name='out_channel_25_real' rate='1'/>
            <port type='in' name='out_channel_28_real' rate='1'/>
            <port type='out' name='in_channel_29_real' rate='1'/>
            <port type='out' name='in_R0x2bb41a0' rate='1'/>
            <port type='in' name='out_R0x2bb41a0' rate='1'/>
        </actor>
        <actor name='0x2bb4320' type='0.5'>
            <port type='out' name='in_channel_24_real' rate='1'/>
            <port type='out' name='in_R0x2bb4320' rate='1'/>
            <port type='in' name='out_R0x2bb4320' rate='1'/>
        </actor>
        <actor name='0x2bb4410' type='prod'>
            <port type='in' name='out_channel_24_real' rate='1'/>
            <port type='in' name='out_channel_29_real' rate='1'/>
            <port type='out' name='in_channel_30_real' rate='1'/>
            <port type='out' name='in_R0x2bb4410' rate='1'/>
            <port type='in' name='out_R0x2bb4410' rate='1'/>
        </actor>
        <actor name='0x2bb4880' type='prod'>
            <port type='in' name='out_channel_30_real' rate='1'/>
            <port type='in' name='out_channel_35_real_vect' rate='1'/>
            <port type='out' name='in_channel_36_real_vect' rate='1'/>
            <port type='out' name='in_R0x2bb4880' rate='1'/>
            <port type='in' name='out_R0x2bb4880' rate='1'/>
        </actor>
        <actor name='0x2bb4970' type='add'>
            <port type='in' name='out_channel_23_real' rate='1'/>
            <port type='in' name='out_channel_36_real_vect' rate='1'/>
            <port type='out' name='in_channel_37_real' rate='1'/>
            <port type='out' name='in_R0x2bb4970' rate='1'/>
            <port type='in' name='out_R0x2bb4970' rate='1'/>
        </actor>
        <actor name='0x7f000c013840' type='INPUT_0'>
            <port type='out' name='in_channel_31_real_vect' rate='1'/>
            <port type='out' name='in_channel_34_real_vect' rate='1'/>
            <port type='out' name='in_R0x7f000c013840' rate='1'/>
            <port type='in' name='out_R0x7f000c013840' rate='1'/>
        </actor>
        <actor name='0x7f000c014ee0' type='fSamplingFreq'>
            <port type='out' name='in_channel_2_int' rate='1'/>
            <port type='out' name='in_R0x7f000c014ee0' rate='1'/>
            <port type='in' name='out_R0x7f000c014ee0' rate='1'/>
        </actor>
        <actor name='0x7f000c016940' type='314.159'>
            <port type='out' name='in_channel_1_real' rate='1'/>
            <port type='out' name='in_R0x7f000c016940' rate='1'/>
            <port type='in' name='out_R0x7f000c016940' rate='1'/>
        </actor>
        <actor name='0x7f000c01f550' type='6283.19'>
            <port type='out' name='in_channel_8_real' rate='1'/>
            <port type='out' name='in_R0x7f000c01f550' rate='1'/>
            <port type='in' name='out_R0x7f000c01f550' rate='1'/>
        </actor>
        <actor name='OUTPUT_0' type='OUTPUT_0'>
            <port type='in' name='out_channel_41_real' rate='1'/>
            <port type='out' name='in_ROUTPUT_0' rate='1'/>
            <port type='in' name='out_ROUTPUT_0' rate='1'/>
        </actor>
        <channel name='channel_0_int' srcActor='0x2bb1870' srcPort='in_channel_0_int' dstActor='0x2bb1920' dstPort='out_channel_0_int' size='1' initialTokens='0'/>
        <channel name='channel_0x2b962a0' srcActor='0x2b962a0' srcPort='in_R0x2b962a0' dstActor='0x2b962a0' dstPort='out_R0x2b962a0' size='1' initialTokens='1'/>
        <channel name='channel_0x2ba41a0' srcActor='0x2ba41a0' srcPort='in_R0x2ba41a0' dstActor='0x2ba41a0' dstPort='out_R0x2ba41a0' size='1' initialTokens='1'/>
        <channel name='channel_0x2bab8a0' srcActor='0x2bab8a0' srcPort='in_R0x2bab8a0' dstActor='0x2bab8a0' dstPort='out_R0x2bab8a0' size='1' initialTokens='1'/>
        <channel name='channel_0x2babca0' srcActor='0x2babca0' srcPort='in_R0x2babca0' dstActor='0x2babca0' dstPort='out_R0x2babca0' size='1' initialTokens='1'/>
        <channel name='channel_0x2bad3d0' srcActor='0x2bad3d0' srcPort='in_R0x2bad3d0' dstActor='0x2bad3d0' dstPort='out_R0x2bad3d0' size='1' initialTokens='1'/>
        <channel name='channel_0x2baf8e0' srcActor='0x2baf8e0' srcPort='in_R0x2baf8e0' dstActor='0x2baf8e0' dstPort='out_R0x2baf8e0' size='1' initialTokens='1'/>
        <channel name='channel_0x2baf9f0' srcActor='0x2baf9f0' srcPort='in_R0x2baf9f0' dstActor='0x2baf9f0' dstPort='out_R0x2baf9f0' size='1' initialTokens='1'/>
        <channel name='channel_0x2bb0720' srcActor='0x2bb0720' srcPort='in_R0x2bb0720' dstActor='0x2bb0720' dstPort='out_R0x2bb0720' size='1' initialTokens='1'/>
        <channel name='channel_0x2bb0850' srcActor='0x2bb0850' srcPort='in_R0x2bb0850' dstActor='0x2bb0850' dstPort='out_R0x2bb0850' size='1' initialTokens='1'/>
        <channel name='channel_0x2bb1870' srcActor='0x2bb1870' srcPort='in_R0x2bb1870' dstActor='0x2bb1870' dstPort='out_R0x2bb1870' size='1' initialTokens='1'/>
        <channel name='channel_0x2bb1920' srcActor='0x2bb1920' srcPort='in_R0x2bb1920' dstActor='0x2bb1920' dstPort='out_R0x2bb1920' size='1' initialTokens='1'/>
        <channel name='channel_0x2bb1a10' srcActor='0x2bb1a10' srcPort='in_R0x2bb1a10' dstActor='0x2bb1a10' dstPort='out_R0x2bb1a10' size='1' initialTokens='1'/>
        <channel name='channel_0x2bb2a10' srcActor='0x2bb2a10' srcPort='in_R0x2bb2a10' dstActor='0x2bb2a10' dstPort='out_R0x2bb2a10' size='1' initialTokens='1'/>
        <channel name='channel_0x2bb35c0' srcActor='0x2bb35c0' srcPort='in_R0x2bb35c0' dstActor='0x2bb35c0' dstPort='out_R0x2bb35c0' size='1' initialTokens='1'/>
        <channel name='channel_0x2bb3760' srcActor='0x2bb3760' srcPort='in_R0x2bb3760' dstActor='0x2bb3760' dstPort='out_R0x2bb3760' size='1' initialTokens='1'/>
        <channel name='channel_0x2bb3850' srcActor='0x2bb3850' srcPort='in_R0x2bb3850' dstActor='0x2bb3850' dstPort='out_R0x2bb3850' size='1' initialTokens='1'/>
        <channel name='channel_0x2bb3940' srcActor='0x2bb3940' srcPort='in_R0x2bb3940' dstActor='0x2bb3940' dstPort='out_R0x2bb3940' size='1' initialTokens='1'/>
        <channel name='channel_0x2bb3a30' srcActor='0x2bb3a30' srcPort='in_R0x2bb3a30' dstActor='0x2bb3a30' dstPort='out_R0x2bb3a30' size='1' initialTokens='1'/>
        <channel name='channel_0x2bb3fe0' srcActor='0x2bb3fe0' srcPort='in_R0x2bb3fe0' dstActor='0x2bb3fe0' dstPort='out_R0x2bb3fe0' size='1' initialTokens='1'/>
        <channel name='channel_0x2bb41a0' srcActor='0x2bb41a0' srcPort='in_R0x2bb41a0' dstActor='0x2bb41a0' dstPort='out_R0x2bb41a0' size='1' initialTokens='1'/>
        <channel name='channel_0x2bb4320' srcActor='0x2bb4320' srcPort='in_R0x2bb4320' dstActor='0x2bb4320' dstPort='out_R0x2bb4320' size='1' initialTokens='1'/>
        <channel name='channel_0x2bb4410' srcActor='0x2bb4410' srcPort='in_R0x2bb4410' dstActor='0x2bb4410' dstPort='out_R0x2bb4410' size='1' initialTokens='1'/>
        <channel name='channel_0x2bb4880' srcActor='0x2bb4880' srcPort='in_R0x2bb4880' dstActor='0x2bb4880' dstPort='out_R0x2bb4880' size='1' initialTokens='1'/>
        <channel name='channel_0x2bb4970' srcActor='0x2bb4970' srcPort='in_R0x2bb4970' dstActor='0x2bb4970' dstPort='out_R0x2bb4970' size='1' initialTokens='1'/>
        <channel name='channel_0x7f000c013840' srcActor='0x7f000c013840' srcPort='in_R0x7f000c013840' dstActor='0x7f000c013840' dstPort='out_R0x7f000c013840' size='1' initialTokens='1'/>
        <channel name='channel_0x7f000c014ee0' srcActor='0x7f000c014ee0' srcPort='in_R0x7f000c014ee0' dstActor='0x7f000c014ee0' dstPort='out_R0x7f000c014ee0' size='1' initialTokens='1'/>
        <channel name='channel_0x7f000c016940' srcActor='0x7f000c016940' srcPort='in_R0x7f000c016940' dstActor='0x7f000c016940' dstPort='out_R0x7f000c016940' size='1' initialTokens='1'/>
        <channel name='channel_0x7f000c01f550' srcActor='0x7f000c01f550' srcPort='in_R0x7f000c01f550' dstActor='0x7f000c01f550' dstPort='out_R0x7f000c01f550' size='1' initialTokens='1'/>
        <channel name='channel_10_real' srcActor='0x2bb0720' srcPort='in_channel_10_real' dstActor='0x2bb0850' dstPort='out_channel_10_real' size='1' initialTokens='0'/>
        <channel name='channel_11_real' srcActor='0x2bb0850' srcPort='in_channel_11_real' dstActor='0x2bb3760' dstPort='out_channel_11_real' size='1' initialTokens='0'/>
        <channel name='channel_12_real' srcActor='0x2bb3760' srcPort='in_channel_12_real' dstActor='0x2bb3850' dstPort='out_channel_12_real' size='1' initialTokens='0'/>
        <channel name='channel_15_real' srcActor='0x2babca0' srcPort='in_channel_15_real' dstActor='0x2bb3850' dstPort='out_channel_15_real' size='1' initialTokens='1'/>
        <channel name='channel_16_real' srcActor='0x2bb3850' srcPort='in_channel_16_real' dstActor='0x2bb3940' dstPort='out_channel_16_real' size='1' initialTokens='0'/>
        <channel name='channel_17_real' srcActor='0x2bb1a10' srcPort='in_channel_17_real' dstActor='0x2bb35c0' dstPort='out_channel_17_real' size='1' initialTokens='0'/>
        <channel name='channel_1_real' srcActor='0x7f000c016940' srcPort='in_channel_1_real' dstActor='0x2baf9f0' dstPort='out_channel_1_real' size='1' initialTokens='0'/>
        <channel name='channel_20_real' srcActor='0x2babca0' srcPort='in_channel_20_real' dstActor='0x2bb35c0' dstPort='out_channel_20_real' size='1' initialTokens='2'/>
        <channel name='channel_21_real' srcActor='0x2bb35c0' srcPort='in_channel_21_real' dstActor='0x2bb3940' dstPort='out_channel_21_real' size='1' initialTokens='0'/>
        <channel name='channel_22_real' srcActor='0x2bb3940' srcPort='in_channel_22_real' dstActor='0x2bb3a30' dstPort='out_channel_22_real' size='1' initialTokens='0'/>
        <channel name='channel_23_real' srcActor='0x2bb3a30' srcPort='in_channel_23_real' dstActor='0x2bb4970' dstPort='out_channel_23_real' size='1' initialTokens='0'/>
        <channel name='channel_24_real' srcActor='0x2bb4320' srcPort='in_channel_24_real' dstActor='0x2bb4410' dstPort='out_channel_24_real' size='1' initialTokens='0'/>
        <channel name='channel_25_real' srcActor='0x2b962a0' srcPort='in_channel_25_real' dstActor='0x2bb41a0' dstPort='out_channel_25_real' size='1' initialTokens='0'/>
        <channel name='channel_26_real' srcActor='0x2bb1a10' srcPort='in_channel_26_real' dstActor='0x2bb2a10' dstPort='out_channel_26_real' size='1' initialTokens='0'/>
        <channel name='channel_27_int' srcActor='0x2ba41a0' srcPort='in_channel_27_int' dstActor='0x2bb2a10' dstPort='out_channel_27_int' size='1' initialTokens='0'/>
        <channel name='channel_28_real' srcActor='0x2bb2a10' srcPort='in_channel_28_real' dstActor='0x2bb41a0' dstPort='out_channel_28_real' size='1' initialTokens='0'/>
        <channel name='channel_29_real' srcActor='0x2bb41a0' srcPort='in_channel_29_real' dstActor='0x2bb4410' dstPort='out_channel_29_real' size='1' initialTokens='0'/>
        <channel name='channel_2_int' srcActor='0x7f000c014ee0' srcPort='in_channel_2_int' dstActor='0x2baf8e0' dstPort='out_channel_2_int' size='1' initialTokens='0'/>
        <channel name='channel_30_real' srcActor='0x2bb4410' srcPort='in_channel_30_real' dstActor='0x2bb4880' dstPort='out_channel_30_real' size='1' initialTokens='0'/>
        <channel name='channel_31_real_vect' srcActor='0x7f000c013840' srcPort='in_channel_31_real_vect' dstActor='0x2bb3fe0' dstPort='out_channel_31_real_vect' size='1' initialTokens='0'/>
        <channel name='channel_34_real_vect' srcActor='0x7f000c013840' srcPort='in_channel_34_real_vect' dstActor='0x2bb3fe0' dstPort='out_channel_34_real_vect' size='1' initialTokens='2'/>
        <channel name='channel_35_real_vect' srcActor='0x2bb3fe0' srcPort='in_channel_35_real_vect' dstActor='0x2bb4880' dstPort='out_channel_35_real_vect' size='1' initialTokens='0'/>
        <channel name='channel_36_real_vect' srcActor='0x2bb4880' srcPort='in_channel_36_real_vect' dstActor='0x2bb4970' dstPort='out_channel_36_real_vect' size='1' initialTokens='0'/>
        <channel name='channel_37_real' srcActor='0x2bb4970' srcPort='in_channel_37_real' dstActor='0x2bab8a0' dstPort='out_channel_37_real' size='1' initialTokens='0'/>
        <channel name='channel_38_real' srcActor='0x2bab8a0' srcPort='in_channel_38_real' dstActor='0x2babca0' dstPort='out_channel_38_real' size='1' initialTokens='0'/>
        <channel name='channel_3_real' srcActor='0x2baf8e0' srcPort='in_channel_3_real' dstActor='0x2baf9f0' dstPort='out_channel_3_real' size='1' initialTokens='0'/>
        <channel name='channel_41_real' srcActor='0x2babca0' srcPort='in_channel_41_real' dstActor='OUTPUT_0' dstPort='out_channel_41_real' size='1' initialTokens='0'/>
        <channel name='channel_4_real' srcActor='0x2baf9f0' srcPort='in_channel_4_real' dstActor='0x2bb1920' dstPort='out_channel_4_real' size='1' initialTokens='0'/>
        <channel name='channel_5_real' srcActor='0x2bb1920' srcPort='in_channel_5_real' dstActor='0x2bb1a10' dstPort='out_channel_5_real' size='1' initialTokens='0'/>
        <channel name='channel_6_real' srcActor='0x2bb1a10' srcPort='in_channel_6_real' dstActor='0x2bb3a30' dstPort='out_channel_6_real' size='1' initialTokens='0'/>
        <channel name='channel_7_real' srcActor='0x2bad3d0' srcPort='in_channel_7_real' dstActor='0x2bb3760' dstPort='out_channel_7_real' size='1' initialTokens='0'/>
        <channel name='channel_8_real' srcActor='0x7f000c01f550' srcPort='in_channel_8_real' dstActor='0x2bb0720' dstPort='out_channel_8_real' size='1' initialTokens='0'/>
        <channel name='channel_9_real' srcActor='0x2baf8e0' srcPort='in_channel_9_real' dstActor='0x2bb0720' dstPort='out_channel_9_real' size='1' initialTokens='0'/>
        <channel name='channel_OUTPUT_0' srcActor='OUTPUT_0' srcPort='in_ROUTPUT_0' dstActor='OUTPUT_0' dstPort='out_ROUTPUT_0' size='1' initialTokens='1'/>
    </sdf>

    <sdfProperties>
        <actorProperties actor='0x2b962a0'>
            <processor type='cluster_0' default='true'>
                <executionTime time='1' />
            </processor>
        </actorProperties>
        <actorProperties actor='0x2ba41a0'>
            <processor type='cluster_0' default='true'>
                <executionTime time='1' />
            </processor>
        </actorProperties>
        <actorProperties actor='0x2bab8a0'>
            <processor type='cluster_0' default='true'>
                <executionTime time='1' />
            </processor>
        </actorProperties>
        <actorProperties actor='0x2babca0'>
            <processor type='cluster_0' default='true'>
                <executionTime time='1' />
            </processor>
        </actorProperties>
        <actorProperties actor='0x2bad3d0'>
            <processor type='cluster_0' default='true'>
                <executionTime time='1' />
            </processor>
        </actorProperties>
        <actorProperties actor='0x2baf8e0'>
            <processor type='cluster_0' default='true'>
                <executionTime time='1' />
            </processor>
        </actorProperties>
        <actorProperties actor='0x2baf9f0'>
            <processor type='cluster_0' default='true'>
                <executionTime time='1' />
            </processor>
        </actorProperties>
        <actorProperties actor='0x2bb0720'>
            <processor type='cluster_0' default='true'>
                <executionTime time='1' />
            </processor>
        </actorProperties>
        <actorProperties actor='0x2bb0850'>
            <processor type='cluster_0' default='true'>
                <executionTime time='1' />
            </processor>
        </actorProperties>
        <actorProperties actor='0x2bb1870'>
            <processor type='cluster_0' default='true'>
                <executionTime time='1' />
            </processor>
        </actorProperties>
        <actorProperties actor='0x2bb1920'>
            <processor type='cluster_0' default='true'>
                <executionTime time='1' />
            </processor>
        </actorProperties>
        <actorProperties actor='0x2bb1a10'>
            <processor type='cluster_0' default='true'>
                <executionTime time='1' />
            </processor>
        </actorProperties>
        <actorProperties actor='0x2bb2a10'>
            <processor type='cluster_0' default='true'>
                <executionTime time='1' />
            </processor>
        </actorProperties>
        <actorProperties actor='0x2bb35c0'>
            <processor type='cluster_0' default='true'>
                <executionTime time='1' />
            </processor>
        </actorProperties>
        <actorProperties actor='0x2bb3760'>
            <processor type='cluster_0' default='true'>
                <executionTime time='1' />
            </processor>
        </actorProperties>
        <actorProperties actor='0x2bb3850'>
            <processor type='cluster_0' default='true'>
                <executionTime time='1' />
            </processor>
        </actorProperties>
        <actorProperties actor='0x2bb3940'>
            <processor type='cluster_0' default='true'>
                <executionTime time='1' />
            </processor>
        </actorProperties>
        <actorProperties actor='0x2bb3a30'>
            <processor type='cluster_0' default='true'>
                <executionTime time='1' />
            </processor>
        </actorProperties>
        <actorProperties actor='0x2bb3fe0'>
            <processor type='cluster_0' default='true'>
                <executionTime time='1' />
            </processor>
        </actorProperties>
        <actorProperties actor='0x2bb41a0'>
            <processor type='cluster_0' default='true'>
                <executionTime time='1' />
            </processor>
        </actorProperties>
        <actorProperties actor='0x2bb4320'>
            <processor type='cluster_0' default='true'>
                <executionTime time='1' />
            </processor>
        </actorProperties>
        <actorProperties actor='0x2bb4410'>
            <processor type='cluster_0' default='true'>
                <executionTime time='1' />
            </processor>
        </actorProperties>
        <actorProperties actor='0x2bb4880'>
            <processor type='cluster_0' default='true'>
                <executionTime time='1' />
            </processor>
        </actorProperties>
        <actorProperties actor='0x2bb4970'>
            <processor type='cluster_0' default='true'>
                <executionTime time='1' />
            </processor>
        </actorProperties>
        <actorProperties actor='0x7f000c013840'>
            <processor type='cluster_0' default='true'>
                <executionTime time='1' />
            </processor>
        </actorProperties>
        <actorProperties actor='0x7f000c014ee0'>
            <processor type='cluster_0' default='true'>
                <executionTime time='1' />
            </processor>
        </actorProperties>
        <actorProperties actor='0x7f000c016940'>
            <processor type='cluster_0' default='true'>
                <executionTime time='1' />
            </processor>
        </actorProperties>
        <actorProperties actor='0x7f000c01f550'>
            <processor type='cluster_0' default='true'>
                <executionTime time='1' />
            </processor>
        </actorProperties>
        <actorProperties actor='OUTPUT_0'>
            <processor type='cluster_0' default='true'>
                <executionTime time='1' />
            </processor>
        </actorProperties>
    </sdfProperties>
</applicationGraph>
</sdf3>
